fma_core/__init__.py
fma_core/conf.py
fma_core/version.py
fma_core/algorithms/__init__.py
fma_core/algorithms/aggregators/__init__.py
fma_core/algorithms/aggregators/common.py
fma_core/algorithms/requirements/__init__.py
fma_core/algorithms/requirements/common.py
fma_core/workflows/__init__.py
fma_core/workflows/aggregator_connectors_factory.py
fma_core/workflows/aggregator_utils.py
fma_core/workflows/api_handler_factory.py
fma_core/workflows/api_handler_utils.py
fma_core/workflows/metadata_connectors_factory.py
fma_core/workflows/model_data_connectors_factory.py
fma_core/workflows/tasks.py
fma_core-0.0.1.dist-info/METADATA
fma_core-0.0.1.dist-info/WHEEL
fma_core-0.0.1.dist-info/top_level.txt
fma_core-0.0.1.dist-info/RECORD
